src/__init__.py
src/gw_calc.py
vasp_pp-0.0.4.dist-info/METADATA
vasp_pp-0.0.4.dist-info/WHEEL
vasp_pp-0.0.4.dist-info/top_level.txt
vasp_pp-0.0.4.dist-info/RECORD
