Metadata-Version: 2.1
Name: vasp-pp
Version: 0.0.4
Summary: Post-processes VASP outputs 
Home-page: https://github.com/brobinson10296/vasp_pp_package
Author: Brian Robinson
Author-email: b.p.robinson102@gmail.com
Keywords: python,VASP,electronic structure,post-processing
Classifier: Development Status :: 1 - Planning
Classifier: Programming Language :: Python :: 3
Classifier: Operating System :: Unix
Classifier: Operating System :: MacOS :: MacOS X
Requires-Dist: numpy
